talos/__init__.py
talos/common/__init__.py
talos/common/async_helper.py
talos/common/cache.py
talos/common/celery.py
talos/common/controller.py
talos/common/decorators.py
talos/common/exporter.py
talos/common/ldap_util.py
talos/common/limitwrapper.py
talos/common/mailer.py
talos/common/process_util.py
talos/common/scheduler.py
talos/core/__init__.py
talos/core/acl.py
talos/core/config.py
talos/core/decorators.py
talos/core/exceptions.py
talos/core/i18n.py
talos/core/logging.py
talos/core/py3compat.py
talos/core/utils.py
talos/core/xmlutils.py
talos/db/__init__.py
talos/db/converter.py
talos/db/crud.py
talos/db/dictbase.py
talos/db/filter_wrapper.py
talos/db/models.py
talos/db/pool.py
talos/db/validator.py
talos/middlewares/__init__.py
talos/middlewares/globalvars.py
talos/middlewares/json_translator.py
talos/middlewares/lazy_init.py
talos/middlewares/limiter.py
talos/server/__init__.py
talos/server/base.py
talos/template/__init__.py
talos/template/tpl_LICENSE.py
talos/template/tpl_MANIFEST_in.py
talos/template/tpl_README_md.py
talos/template/tpl_VERSION.py
talos/template/tpl_init_py.py
talos/template/tpl_requirements_txt.py
talos/template/tpl_setup_cfg.py
talos/template/tpl_setup_py.py
talos/template/tpl_tox_ini.py
talos/template/alembic/__init__.py
talos/template/alembic/tpl_alembic_ini.py
talos/template/alembic/migration/__init__.py
talos/template/alembic/migration/tpl_README.py
talos/template/alembic/migration/tpl_env_py.py
talos/template/alembic/migration/tpl_script_py.py
talos/template/apps/__init__.py
talos/template/apps/tpl_app_api_py.py
talos/template/apps/tpl_app_controller_py.py
talos/template/apps/tpl_init_py.py
talos/template/apps/tpl_route_py.py
talos/template/db/__init__.py
talos/template/db/tpl_init_py.py
talos/template/db/tpl_models_py.py
talos/template/etc/__init__.py
talos/template/etc/tpl_gunicorn_py.py
talos/template/etc/tpl_project_conf.py
talos/template/etc/locale/__init__.py
talos/template/etc/locale/en/__init__.py
talos_api-1.3.7.dist-info/LICENSE
talos_api-1.3.7.dist-info/METADATA
talos_api-1.3.7.dist-info/WHEEL
talos_api-1.3.7.dist-info/entry_points.txt
talos_api-1.3.7.dist-info/top_level.txt
talos_api-1.3.7.dist-info/RECORD
