Metadata-Version: 2.1
Name: talos-api
Version: 1.3.7
Summary: A Falcon Base, Powerful RESTful API Framework, with SQLAlchemy integrated
Home-page: https://gitee.com/wu.jianjun/talos
Author: Roy
Author-email: wjjroy@outlook.com
License: Apache License 2.0
Keywords: talos automation restful rest api celery sqlalchemy falcon
Classifier: Development Status :: 5 - Production/Stable 
Classifier: Intended Audience :: Developers
Classifier: License :: OSI Approved :: Apache Software License 
Classifier: Topic :: Software Development :: Libraries
Classifier: Programming Language :: Python :: 2
Classifier: Programming Language :: Python :: 2.7
Classifier: Programming Language :: Python :: 3
Classifier: Programming Language :: Python :: 3.6
Classifier: Programming Language :: Python :: 3.7
Classifier: Programming Language :: Python :: 3.8
Classifier: Operating System :: OS Independent
License-File: LICENSE
Requires-Dist: falcon (==2.0.0)
Requires-Dist: six (>=1.9.0)
Requires-Dist: SQLAlchemy (<1.4.0,>=1.1.0)
Requires-Dist: mako
Requires-Dist: requests
Requires-Dist: limits
Requires-Dist: celery (<5.0.0)
Requires-Dist: dogpile.cache
Requires-Dist: ipaddress ; python_version < "3.3"
Provides-Extra: testing
Requires-Dist: pytest ; extra == 'testing'
Requires-Dist: pytest-runner ; extra == 'testing'
Requires-Dist: pytest-html ; extra == 'testing'
Requires-Dist: pytest-cov ; extra == 'testing'
Requires-Dist: pytest-mock ; extra == 'testing'
